norduniclient/__init__.py
norduniclient/contextmanager.py
norduniclient/core.py
norduniclient/exceptions.py
norduniclient/helpers.py
norduniclient/models.py
norduniclient/testing.py
norduniclient-1.4.1.dist-info/LICENSE
norduniclient-1.4.1.dist-info/METADATA
norduniclient-1.4.1.dist-info/WHEEL
norduniclient-1.4.1.dist-info/top_level.txt
norduniclient-1.4.1.dist-info/RECORD
