Metadata-Version: 2.1
Name: norduniclient
Version: 1.4.1
Summary: Neo4j (>=3.2.2) database client using bolt for NORDUnet network inventory
Home-page: https://github.com/NORDUnet/python-norduniclient
Author: Johan Lundberg
Author-email: lundberg@nordu.net
License: Apache License, Version 2.0
License-File: LICENSE
Requires-Dist: neo4j-driver (<2.0)
Provides-Extra: testing
Requires-Dist: nose ; extra == 'testing'
Requires-Dist: coverage ; extra == 'testing'
Requires-Dist: nosexcover ; extra == 'testing'
